FinData/accounts.py
FinData/client.py
FinData/constants.py
financial_data_client-0.0.1.dist-info/METADATA
financial_data_client-0.0.1.dist-info/WHEEL
financial_data_client-0.0.1.dist-info/top_level.txt
financial_data_client-0.0.1.dist-info/RECORD
