Metadata-Version: 2.1
Name: financial-data-client
Version: 0.0.1
Summary: Package for easily retrieving price data from multiple sources
Home-page: https://github.com/maxhleonard/financial-data-client
Author: Max Leonard
Author-email: maxhleonard@gmail.com
License: UNKNOWN
Project-URL: Bug Tracker, https://github.com/pypa/sampleproject/issues
Platform: UNKNOWN
Classifier: Programming Language :: Python :: 3
Classifier: License :: OSI Approved :: MIT License
Classifier: Operating System :: OS Independent
Requires-Python: >=3.6
Requires-Dist: pandas
Requires-Dist: python-binance
Requires-Dist: kucoin-python
